<?xml version="1.0"?>
<exportedFiles>
  <exportedFile url="\Portal\SlxClient\SupportFiles\help\Content\Reporting\repmain.htm" timeStamp="2010-08-11T04:05:48.3100" />
  <exportedFile url="\Portal\SlxClient\SupportFiles\help\Content\Reporting\reportconditionformulas.htm" timeStamp="2010-08-11T04:05:48.3100" />
  <exportedFile url="\Portal\SlxClient\SupportFiles\help\Content\Reporting\reportdetailviews.htm" timeStamp="2010-08-11T04:05:48.3270" />
  <exportedFile url="\Portal\SlxClient\SupportFiles\help\Content\Reporting\reportfilter.htm" timeStamp="2010-08-11T04:05:48.3100" />
  <exportedFile url="\Portal\SlxClient\SupportFiles\help\Content\Reporting\reportoverview.htm" timeStamp="2010-08-11T04:05:48.3100" />
  <exportedFile url="\Portal\SlxClient\SupportFiles\help\Content\Reporting\reportprompts.htm" timeStamp="2010-08-11T04:05:48.3100" />
  <exportedFile url="\Portal\SlxClient\SupportFiles\help\Content\Reporting\reportrun.htm" timeStamp="2010-08-11T04:05:48.3400" />
  <exportedFile url="\Portal\SlxClient\SupportFiles\help\Content\Reporting\reportshare.htm" timeStamp="2010-08-11T04:05:48.3400" />
  <exportedFile url="\Portal\SlxClient\SupportFiles\help\Content\Reporting\reporttroubleshooting.htm" timeStamp="2010-08-11T04:05:48.3570" />
</exportedFiles>